{
  "title": "Exapostilarion 9",
  "content": "Though the doors were locked, O Lord, * You entered and filled Your apostles with the Holy Spirit,* and breathing over them, You gave them Your peace.* You said to them: Whose sins you forgive, they are forgiven;* whose sins you bind, they are bound.* After eight days You showed Thomas Your hands and Your side.* With them, therefore, we cry to You: You are my Lord and my God!",
  "source": "Stamford Octoechos",
  "_aliases": [
    "eothinon_9_exapostilarion"
  ],
  "_original_id": "eothinon.eothinon_9_exapostilarion"
}